{".class": "MypyFile", "_fullname": "project_multiclipboard", "is_partial_stub_package": false, "is_stub": false, "names": {".class": "SymbolTable", "__doc__": {".class": "SymbolTableNode", "kind": "Gdef", "node": {".class": "Var", "flags": ["is_ready"], "fullname": "project_multiclipboard.__doc__", "name": "__doc__", "type": "builtins.str"}}, "__file__": {".class": "SymbolTableNode", "kind": "Gdef", "node": {".class": "Var", "flags": ["is_ready"], "fullname": "project_multiclipboard.__file__", "name": "__file__", "type": "builtins.str"}}, "__name__": {".class": "SymbolTableNode", "kind": "Gdef", "node": {".class": "Var", "flags": ["is_ready"], "fullname": "project_multiclipboard.__name__", "name": "__name__", "type": "builtins.str"}}, "__package__": {".class": "SymbolTableNode", "kind": "Gdef", "node": {".class": "Var", "flags": ["is_ready"], "fullname": "project_multiclipboard.__package__", "name": "__package__", "type": "builtins.str"}}, "mcbShelf": {".class": "SymbolTableNode", "kind": "Gdef", "node": {".class": "Var", "flags": [], "fullname": "project_multiclipboard.mcbShelf", "name": "mcbShelf", "type": "shelve.DbfilenameShelf"}}, "pyperclip": {".class": "SymbolTableNode", "kind": "Gdef", "node": {".class": "Var", "flags": ["is_suppressed_import", "is_ready"], "fullname": "project_multiclipboard.pyperclip", "name": "pyperclip", "type": {".class": "AnyType", "missing_import_name": "project_multiclipboard.pyperclip", "source_any": null, "type_of_any": 3}}}, "shelve": {".class": "SymbolTableNode", "cross_ref": "shelve", "kind": "Gdef"}, "sys": {".class": "SymbolTableNode", "cross_ref": "sys", "kind": "Gdef"}}, "path": "/Users/noesautel/Documents/GitHub/diverse/project_multiclipboard.py"}